sage_imap/__init__.py
sage_imap/decorators.py
sage_imap/exceptions.py
sage_imap/helpers/__init__.py
sage_imap/helpers/enums.py
sage_imap/helpers/search.py
sage_imap/helpers/typings.py
sage_imap/models/__init__.py
sage_imap/models/email.py
sage_imap/models/message.py
sage_imap/services/__init__.py
sage_imap/services/client.py
sage_imap/services/flag.py
sage_imap/services/folder.py
sage_imap/services/mailbox.py
sage_imap/utils.py
python_sage_imap-0.4.8.dist-info/LICENSE
python_sage_imap-0.4.8.dist-info/METADATA
python_sage_imap-0.4.8.dist-info/WHEEL
python_sage_imap-0.4.8.dist-info/RECORD
