Metadata-Version: 2.1
Name: python-sage-imap
Version: 0.4.8
Summary: A Python package for managing IMAP connections and email operations.
Home-page: https://github.com/sageteamorg/python-sage-imap
License: MIT
Keywords: python,imap,email,mailbox,python-packages
Author: Sepehr Akbarzadeh
Author-email: sepehr@sageteam.org
Requires-Python: >=3.10,<4.0
Classifier: Intended Audience :: Developers
Classifier: License :: OSI Approved :: MIT License
Classifier: Operating System :: OS Independent
Classifier: Programming Language :: Python :: 3
Classifier: Programming Language :: Python :: 3.10
Classifier: Programming Language :: Python :: 3.11
Classifier: Programming Language :: Python :: 3.12
Requires-Dist: requests (>=2.32.3,<3.0.0)
Project-URL: Documentation, https://python-sage-imap.readthedocs.io/en/latest/
Project-URL: Issues, https://github.com/sageteamorg/python-sage-imap/issues
Project-URL: Repository, https://github.com/sageteamorg/python-sage-imap
Project-URL: Source Code, https://github.com/sageteamorg/python-sage-imap
